nonebot_plugin_group_whitelist-0.9.2.dist-info/METADATA
nonebot_plugin_group_whitelist-0.9.2.dist-info/WHEEL
nonebot_plugin_group_whitelist/.git/COMMIT_EDITMSG
nonebot_plugin_group_whitelist/.git/FETCH_HEAD
nonebot_plugin_group_whitelist/.git/HEAD
nonebot_plugin_group_whitelist/.git/ORIG_HEAD
nonebot_plugin_group_whitelist/.git/config
nonebot_plugin_group_whitelist/.git/description
nonebot_plugin_group_whitelist/.git/hooks/applypatch-msg.sample
nonebot_plugin_group_whitelist/.git/hooks/commit-msg.sample
nonebot_plugin_group_whitelist/.git/hooks/fsmonitor-watchman.sample
nonebot_plugin_group_whitelist/.git/hooks/post-update.sample
nonebot_plugin_group_whitelist/.git/hooks/pre-applypatch.sample
nonebot_plugin_group_whitelist/.git/hooks/pre-commit.sample
nonebot_plugin_group_whitelist/.git/hooks/pre-merge-commit.sample
nonebot_plugin_group_whitelist/.git/hooks/pre-push.sample
nonebot_plugin_group_whitelist/.git/hooks/pre-rebase.sample
nonebot_plugin_group_whitelist/.git/hooks/pre-receive.sample
nonebot_plugin_group_whitelist/.git/hooks/prepare-commit-msg.sample
nonebot_plugin_group_whitelist/.git/hooks/push-to-checkout.sample
nonebot_plugin_group_whitelist/.git/hooks/update.sample
nonebot_plugin_group_whitelist/.git/index
nonebot_plugin_group_whitelist/.git/info/exclude
nonebot_plugin_group_whitelist/.git/logs/HEAD
nonebot_plugin_group_whitelist/.git/logs/refs/heads/main
nonebot_plugin_group_whitelist/.git/logs/refs/remotes/origin/HEAD
nonebot_plugin_group_whitelist/.git/logs/refs/remotes/origin/main
nonebot_plugin_group_whitelist/.git/objects/02/ca2abf226cc1b0d6fe86cb32cafa7dac78b1c9
nonebot_plugin_group_whitelist/.git/objects/09/09cbf5c843522b88bae77f025252c279356f80
nonebot_plugin_group_whitelist/.git/objects/0d/df7b69036d35392b12cec61683285677ab8442
nonebot_plugin_group_whitelist/.git/objects/10/5ce2da2d6447d11dfe32bfb846c3d5b199fc99
nonebot_plugin_group_whitelist/.git/objects/11/e0a0d971c6dd08d64fb946f65aa27d3218c986
nonebot_plugin_group_whitelist/.git/objects/12/0bf08582c35f4ef4b91461f78aa58ff8dd8e05
nonebot_plugin_group_whitelist-0.9.2.dist-info/RECORD
