Metadata-Version: 2.1
Name: nonebot-plugin-group-whitelist
Version: 0.9.2
Summary: 适用于NoneBot2的群聊白名单
Home-page: https://github.com/Rikka-desu/nonebot_plugin_group_whitelist
Author-Email: 轩某 <xuan_mou@outlook.com>
License: MIT
Project-URL: Homepage, https://github.com/Rikka-desu/nonebot_plugin_group_whitelist
Requires-Python: >=3.8
Requires-Dist: nonebot2>=2.0.0
Requires-Dist: nonebot-plugin-localstore>=0.5.0
Requires-Dist: nonebot-adapter-onebot
